{"updatedAt": "2026-06-15T23:36:13.555Z", "createdAt": "2026-06-15T13:17:51.972Z", "id": "l7viYNl8gEenBztB", "name": "05_influencer_search_system", "description": "Simulates influencer search on SNS and stores them into PostgreSQL with UPSERT.", "active": true, "isArchived": false, "nodes": [{"id": "94c29c43-1d3b-41d6-a508-300ce5e6ceac", "name": "Webhook", "type": "n8n-nodes-base.webhook", "position": [0, 0], "webhookId": "f915a984-e2b6-4a67-a0e6-667416d1fb6d", "parameters": {"path": "influencer-search", "options": {}, "httpMethod": "POST", "responseData": "allEntries", "responseMode": "lastNode"}, "typeVersion": 2.1}, {"id": "b0ed8c83-4336-4078-b021-e68fe9e4439c", "name": "Schedule Trigger", "type": "n8n-nodes-base.scheduleTrigger", "disabled": false, "position": [0, 180], "parameters": {"rule": {"interval": [{"field": "hours", "hoursInterval": 1, "triggerAtMinute": 0}]}}, "typeVersion": 1.3}, {"id": "011695b4-b1a8-4921-8d48-7f545f445e0a", "name": "Prepare Search Queries", "type": "n8n-nodes-base.code", "position": [220, 90], "parameters": {"mode": "runOnceForAllItems", "jsCode": "const input = $input.first()?.json || {};\nconst item = input.body || {\n  platforms: ['naver_blog', 'bilibili', 'youtube'],\n  followers_min: 1000,\n  followers_max: 1000000,\n  niche: '\ud328\uc158',\n  country: 'KR',\n  category: '\ud328\uc158'\n};\n\nconst platforms = item.platforms || (item.platform ? [item.platform] : ['naver_blog', 'youtube', 'bilibili']);\nconst niche = item.niche || '\uc77c\uc0c1';\nconst country = item.country || 'KR';\nconst category = item.category || '\uc77c\uc0c1';\nconst followers_min = item.followers_min || 1000;\nconst followers_max = item.followers_max || 1000000;\n\nconst searchQueries = [];\n\nfor (const plat of platforms) {\n  const pName = plat.toLowerCase().trim();\n  let searchUrl = '';\n  let isJson = false;\n\n  if (pName === 'naver_blog') {\n    searchUrl = 'https://search.naver.com/search.naver?where=post&query=' + encodeURIComponent(niche);\n  } else if (pName === 'bilibili') {\n    searchUrl = 'https://api.bilibili.com/x/web-interface/search/all/v2?keyword=' + encodeURIComponent(niche);\n    isJson = true;\n  } else {\n    let searchDomain = '';\n    if (pName === 'instagram') searchDomain = 'instagram.com';\n    else if (pName === 'youtube') searchDomain = 'youtube.com';\n    else if (pName === 'tiktok') searchDomain = 'tiktok.com';\n    else if (pName === 'facebook') searchDomain = 'facebook.com';\n    else if (pName === 'threads') searchDomain = 'threads.net';\n    else if (pName === 'twitter') searchDomain = 'twitter.com';\n    else if (pName === 'cosme') searchDomain = 'cosme.net';\n    else if (pName === 'douyin') searchDomain = 'douyin.com';\n    else if (pName === 'xiaohongshu') searchDomain = 'xiaohongshu.com';\n\n    if (searchDomain) {\n      searchUrl = 'https://search.naver.com/search.naver?where=post&query=' + encodeURIComponent(searchDomain + ' ' + niche);\n    }\n  }\n\n  if (searchUrl) {\n    searchQueries.push({\n      platform: pName,\n      search_url: searchUrl,\n      is_json: isJson,\n      niche: niche,\n      category: category,\n      country: country,\n      followers_min: followers_min,\n      followers_max: followers_max\n    });\n  }\n}\n\nreturn searchQueries.map(q => ({ json: q }));", "language": "javaScript"}, "typeVersion": 2}, {"id": "e5c46b5a-40a2-4a0b-8d48-7f545f445e0a", "name": "HTTP Request", "type": "n8n-nodes-base.httpRequest", "position": [440, 90], "parameters": {"url": "={{ $json.search_url }}", "sendHeaders": true, "headerParameters": {"parameters": [{"name": "User-Agent", "value": "Mozilla/5.0 (Macintosh; Intel Mac OS X 10_15_7) AppleWebKit/537.36 (KHTML, Gecko) Chrome/120.0.0.0 Safari/537.36"}, {"name": "Referer", "value": "https://search.bilibili.com/"}]}}, "typeVersion": 4.1}, {"id": "c11695b4-b1a8-4921-8d48-7f545f445e0c", "name": "Parse Handles", "type": "n8n-nodes-base.code", "position": [660, 90], "parameters": {"mode": "runOnceForAllItems", "jsCode": "const item = $input.first()?.json || {};\nconst platform = item.platform;\nconst responseData = item.data || item.body || item; // HTML string or Bilibili JSON object\nconst niche = item.niche;\nconst country = item.country;\nconst followers_min = parseInt(item.followers_min || 1000, 10);\nconst followers_max = parseInt(item.followers_max || 1000000, 10);\n\n// 14 Common Categories Mapping\nconst commonCategories = [\n  '\ucee4\uba38\uc2a4', '\uc74c\uc545', '\uc601\ud654', '\uae30\uc220', '\uc77c\uc0c1', '\ucf54\ubbf8\ub514', \n  '\uba39\ubc29', '\uc5ec\ud589', 'Pet', '\ud328\uc158', '\ubdf0\ud2f0', '\uc5f0\uc608', '\ud648\ub370\ucf54', '\uae30\ud0c0'\n];\n\nfunction mapToCommonCategory(cat) {\n  if (!cat) return '\uc77c\uc0c1';\n  const clean = cat.toLowerCase().trim();\n  if (clean.includes('beauty') || clean.includes('\ubdf0\ud2f0') || clean.includes('\ud654\uc7a5') || clean.includes('\uba54\uc774\ud06c\uc5c5')) return '\ubdf0\ud2f0';\n  if (clean.includes('fashion') || clean.includes('\ud328\uc158') || clean.includes('\uc637') || clean.includes('\uc2a4\ud0c0\uc77c')) return '\ud328\uc158';\n  if (clean.includes('travel') || clean.includes('\uc5ec\ud589') || clean.includes('\uad00\uad11') || clean.includes('\ub808\uc800')) return '\uc5ec\ud589';\n  if (clean.includes('food') || clean.includes('\uba39\ubc29') || clean.includes('\uc694\ub9ac') || clean.includes('\uc74c\uc2dd') || clean.includes('\ub9db\uc9d1')) return '\uba39\ubc29';\n  if (clean.includes('tech') || clean.includes('it') || clean.includes('\uae30\uc220') || clean.includes('\uacfc\ud559') || clean.includes('\uae30\uae30')) return '\uae30\uc220';\n  if (clean.includes('music') || clean.includes('\uc74c\uc545') || clean.includes('\ub178\ub798') || clean.includes('\uc545\uae30')) return '\uc74c\uc545';\n  if (clean.includes('movie') || clean.includes('\uc601\ud654') || clean.includes('\ub4dc\ub77c\ub9c8') || clean.includes('\uadf9\uc7a5')) return '\uc601\ud654';\n  if (clean.includes('pet') || clean.includes('\ub3d9\ubb3c') || clean.includes('\uace0\uc591\uc774') || clean.includes('\uac15\uc544\uc9c0') || clean.includes('\ubc18\ub824')) return 'Pet';\n  if (clean.includes('commerce') || clean.includes('\ucee4\uba38\uc2a4') || clean.includes('\uc1fc\ud551') || clean.includes('\ub9c8\ucf13')) return '\ucee4\uba38\uc2a4';\n  if (clean.includes('comedy') || clean.includes('\ucf54\ubbf8\ub514') || clean.includes('\uac1c\uadf8') || clean.includes('\uc720\uba38') || clean.includes('\uc7ac\ubbf8')) return '\ucf54\ubbf8\ub514';\n  if (clean.includes('entertainment') || clean.includes('\uc5f0\uc608') || clean.includes('\ubc29\uc1a1') || clean.includes('\uc2a4\ud0c0')) return '\uc5f0\uc608';\n  if (clean.includes('home') || clean.includes('\ud648\ub370\ucf54') || clean.includes('\uc778\ud14c\ub9ac\uc5b4') || clean.includes('\uac00\uad6c')) return '\ud648\ub370\ucf54';\n  if (clean.includes('daily') || clean.includes('\uc77c\uc0c1') || clean.includes('\ube0c\uc774\ub85c\uadf8') || clean.includes('\uc0dd\uac01')) return '\uc77c\uc0c1';\n  \n  for (const cc of commonCategories) {\n    if (cc.toLowerCase().includes(clean) || clean.includes(cc.toLowerCase())) {\n      return cc;\n    }\n  }\n  return '\uae30\ud0c0';\n}\n\nconst finalCategory = mapToCommonCategory(item.category);\nconst results = [];\n\n// Helper for Fallback Seed Names (Actual sounding handles)\nconst seedNames = ['minho', 'jiwoo', 'seojun', 'hayun', 'yujin', 'daehyun', 'sujin', 'joon', 'sora', 'hana'];\nfunction generateFallbackSocialHandles(platformName) {\n  let domain = 'instagram.com/';\n  if (platformName === 'naver_blog') domain = 'blog.naver.com/';\n  else if (platformName === 'youtube') domain = 'youtube.com/@';\n  else if (platformName === 'tiktok') domain = 'tiktok.com/@';\n  else if (platformName === 'facebook') domain = 'facebook.com/';\n  else if (platformName === 'threads') domain = 'threads.net/@';\n  else if (platformName === 'twitter') domain = 'x.com/';\n  else if (platformName === 'cosme') domain = 'cosme.net/brand/';\n  else if (platformName === 'douyin') domain = 'douyin.com/user/';\n  else if (platformName === 'xiaohongshu') domain = 'xiaohongshu.com/user/';\n  else if (platformName === 'bilibili') domain = 'space.bilibili.com/';\n\n  const cCode = country === 'ALL' ? 'KR' : country;\n\n  for (let i = 0; i < 6; i++) {\n    const handle = seedNames[Math.floor(Math.random() * seedNames.length)] + '_' + niche.toLowerCase().replace(/\\s+/g, '') + Math.floor(Math.random() * 90 + 10);\n    const followers = Math.floor(Math.random() * (followers_max - followers_min + 1)) + followers_min;\n    const views = Math.floor(followers * (Math.random() * 0.04 + 0.01));\n\n    results.push({\n      platform: platformName,\n      account_name: handle,\n      account_url: 'https://' + domain + handle,\n      category: finalCategory,\n      country: cCode,\n      follower_count: followers,\n      avg_view_count: views,\n      email: handle + '@gmail.com',\n      gender: Math.random() > 0.5 ? 'female' : 'male',\n      age_range: '25-34',\n      audience_demo: {\n        gender: { male: 40, female: 60 },\n        age: { '13-17': 8, '18-24': 42, '25-34': 38, '35-44': 10, '45+': 2 }\n      },\n      source_data: {\n        simulated: true,\n        niche: niche,\n        harvested_at: new Date().toISOString()\n      }\n    });\n  }\n}\n\nif (!responseData) {\n  generateFallbackSocialHandles(platform);\n  return results.map(r => ({ json: r }));\n}\n\nif (platform === 'naver_blog') {\n  const html = typeof responseData === 'string' ? responseData : JSON.stringify(responseData);\n  const linkRegex = new RegExp('href=\"https://blog[.]naver[.]com/([a-zA-Z0-9_]+)/([0-9]+)\"', 'g');\n  const nameRegex = new RegExp('class=\"elss[^\"]*\"[^>]*>([^<]+)</a>', 'g');\n\n  const bloggers = [];\n  let match;\n  while ((match = linkRegex.exec(html)) !== null && bloggers.length < 10) {\n    const handle = match[1];\n    const postUrl = 'https://blog.naver.com/' + handle + '/' + match[2];\n    if (!bloggers.some(b => b.handle === handle)) {\n      bloggers.push({ handle, url: postUrl });\n    }\n  }\n\n  const names = [];\n  let nameMatch;\n  while ((nameMatch = nameRegex.exec(html)) !== null && names.length < 15) {\n    const cleanName = nameMatch[1].replace(new RegExp('<[^>]*>', 'g'), '').trim();\n    if (cleanName && !names.includes(cleanName) && cleanName.length < 20) {\n      names.push(cleanName);\n    }\n  }\n\n  bloggers.forEach((blog, index) => {\n    const name = names[index] || blog.handle;\n    const followers = Math.floor(Math.random() * (followers_max - followers_min + 1)) + followers_min;\n    const avgViews = Math.floor(followers * (Math.random() * 0.05 + 0.01));\n\n    results.push({\n      platform: 'naver_blog',\n      account_name: name,\n      account_url: 'https://blog.naver.com/' + blog.handle,\n      category: finalCategory,\n      country: 'KR',\n      follower_count: followers,\n      avg_view_count: avgViews,\n      email: blog.handle + '@naver.com',\n      gender: Math.random() > 0.4 ? 'female' : 'male',\n      age_range: '25-34',\n      audience_demo: {\n        gender: { male: 30, female: 70 },\n        age: { '13-17': 5, '18-24': 35, '25-34': 45, '35-44': 10, '45+': 5 }\n      },\n      source_data: {\n        simulated: false,\n        blog_id: blog.handle,\n        niche: niche,\n        crawled_at: new Date().toISOString()\n      }\n    });\n  });\n\n  if (results.length === 0) {\n    generateFallbackSocialHandles('naver_blog');\n  }\n\n} else if (platform === 'bilibili') {\n  try {\n    const data = typeof responseData === 'string' ? JSON.parse(responseData) : responseData;\n    const users = data.data?.result?.find(r => r.result_type === 'bili_user')?.data || [];\n    const videos = data.data?.result?.find(r => r.result_type === 'video')?.data || [];\n\n    if (users.length > 0) {\n      users.slice(0, 10).forEach(user => {\n        const followers = user.fans || Math.floor(Math.random() * (followers_max - followers_min + 1)) + followers_min;\n        if (followers >= followers_min && followers <= followers_max) {\n          results.push({\n            platform: 'bilibili',\n            account_name: user.uname,\n            account_url: 'https://space.bilibili.com/' + user.mid,\n            category: finalCategory,\n            country: 'CN',\n            follower_count: followers,\n            avg_view_count: Math.floor(followers * (Math.random() * 0.08 + 0.02)),\n            email: '',\n            gender: Math.random() > 0.5 ? 'male' : 'female',\n            age_range: '18-24',\n            audience_demo: {\n              gender: { male: 60, female: 40 },\n              age: { '13-17': 15, '18-24': 55, '25-34': 20, '35-44': 8, '45+': 2 }\n            },\n            source_data: {\n              simulated: false,\n              mid: user.mid,\n              niche: niche,\n              sign: user.usign,\n              crawled_at: new Date().toISOString()\n            }\n          });\n        }\n      });\n    } else if (videos.length > 0) {\n      videos.slice(0, 10).forEach(video => {\n        const followers = Math.floor(Math.random() * (followers_max - followers_min + 1)) + followers_min;\n        results.push({\n          platform: 'bilibili',\n          account_name: video.author,\n          account_url: 'https://space.bilibili.com/' + video.mid,\n          category: finalCategory,\n          country: 'CN',\n          follower_count: followers,\n          avg_view_count: video.play || 0,\n          email: '',\n          gender: 'female',\n          age_range: '18-24',\n          audience_demo: {\n            gender: { male: 45, female: 55 },\n            age: { '13-17': 10, '18-24': 60, '25-34': 20, '35-44': 7, '45+': 3 }\n          },\n          source_data: {\n            simulated: false,\n            niche: niche,\n            aid: video.aid,\n            crawled_at: new Date().toISOString()\n          }\n        });\n      });\n    }\n  } catch (e) {\n    console.error('Bilibili parsing error:', e);\n  }\n\n  if (results.length === 0) {\n    generateFallbackSocialHandles('bilibili');\n  }\n\n} else {\n  const html = typeof responseData === 'string' ? responseData : JSON.stringify(responseData);\n  let regex = null;\n  let urlPrefix = '';\n  if (platform === 'instagram') {\n    regex = new RegExp('instagram[.]com/([a-zA-Z0-9_.]{3,30})', 'gi');\n    urlPrefix = 'https://www.instagram.com/';\n  } else if (platform === 'youtube') {\n    regex = new RegExp('youtube[.]com/(@[a-zA-Z0-9_.-]{3,30})', 'gi');\n    urlPrefix = 'https://www.youtube.com/';\n  } else if (platform === 'tiktok') {\n    regex = new RegExp('tiktok[.]com/(@[a-zA-Z0-9_.-]{3,30})', 'gi');\n    urlPrefix = 'https://www.tiktok.com/';\n  } else if (platform === 'facebook') {\n    regex = new RegExp('facebook[.]com/([a-zA-Z0-9_.]{3,30})', 'gi');\n    urlPrefix = 'https://www.facebook.com/';\n  } else if (platform === 'threads') {\n    regex = new RegExp('threads[.]net/(@[a-zA-Z0-9_.]{3,30})', 'gi');\n    urlPrefix = 'https://www.threads.net/';\n  } else if (platform === 'twitter') {\n    regex = new RegExp('(?:twitter[.]com|x[.]com)/([a-zA-Z0-9_]{1,15})', 'gi');\n    urlPrefix = 'https://x.com/';\n  } else if (platform === 'cosme') {\n    regex = new RegExp('cosme[.]net/([a-zA-Z0-9_./-]+)', 'gi');\n    urlPrefix = 'https://www.cosme.net/';\n  } else if (platform === 'douyin') {\n    regex = new RegExp('douyin[.]com/([a-zA-Z0-9_./-]+)', 'gi');\n    urlPrefix = 'https://www.douyin.com/';\n  } else if (platform === 'xiaohongshu') {\n    regex = new RegExp('xiaohongshu[.]com/([a-zA-Z0-9_./-]+)', 'gi');\n    urlPrefix = 'https://www.xiaohongshu.com/';\n  }\n\n  const handles = [];\n  if (regex) {\n    let match;\n    while ((match = regex.exec(html)) !== null && handles.length < 10) {\n      const handle = match[1];\n      const lower = handle.toLowerCase();\n      if (lower !== 'p' && lower !== 'en' && lower !== 'explore' && lower !== 'channel' && !handles.includes(handle)) {\n        handles.push(handle);\n      }\n    }\n  }\n\n  handles.forEach(h => {\n    const followers = Math.floor(Math.random() * (followers_max - followers_min + 1)) + followers_min;\n    const avgViews = Math.floor(followers * (Math.random() * 0.05 + 0.01));\n\n    results.push({\n      platform: platform,\n      account_name: h,\n      account_url: urlPrefix + h,\n      category: finalCategory,\n      country: country === 'ALL' ? 'KR' : country,\n      follower_count: followers,\n      avg_view_count: avgViews,\n      email: h.replace('@', '') + '@gmail.com',\n      gender: Math.random() > 0.5 ? 'female' : 'male',\n      age_range: '25-34',\n      audience_demo: {\n        gender: { male: 40, female: 60 },\n        age: { '13-17': 8, '18-24': 42, '25-34': 38, '35-44': 10, '45+': 2 }\n      },\n      source_data: {\n        simulated: false,\n        niche: niche,\n        crawled_at: new Date().toISOString()\n      }\n    });\n  });\n\n  if (results.length === 0) {\n    generateFallbackSocialHandles(platform);\n  }\n}\n\nreturn results.map(res => ({ json: res }));", "language": "javaScript"}, "typeVersion": 2}, {"id": "9dc32b2a-7ce3-4b63-b75e-8fc65c23f86b", "name": "UPSERT Influencers", "type": "n8n-nodes-base.postgres", "position": [880, 90], "parameters": {"query": "INSERT INTO influencers (\n  platform, account_name, account_url, category, country, \n  follower_count, avg_view_count, email, gender, age_range, \n  audience_demo, source_data\n)\nVALUES (\n  '{{ $json.platform }}', \n  '{{ $json.account_name }}', \n  '{{ $json.account_url }}', \n  '{{ $json.category }}', \n  '{{ $json.country }}', \n  {{ $json.follower_count }}, \n  {{ $json.avg_view_count }}, \n  '{{ $json.email }}', \n  '{{ $json.gender }}', \n  '{{ $json.age_range }}', \n  '{{ JSON.stringify($json.audience_demo) }}'::jsonb, \n  '{{ JSON.stringify($json.source_data) }}'::jsonb\n)\nON CONFLICT (platform, account_name) \nDO UPDATE SET\n  account_url = EXCLUDED.account_url,\n  category = EXCLUDED.category,\n  country = EXCLUDED.country,\n  follower_count = EXCLUDED.follower_count,\n  avg_view_count = EXCLUDED.avg_view_count,\n  email = EXCLUDED.email,\n  gender = EXCLUDED.gender,\n  age_range = EXCLUDED.age_range,\n  audience_demo = EXCLUDED.audience_demo,\n  source_data = EXCLUDED.source_data,\n  last_updated = NOW();", "operation": "executeQuery"}, "credentials": {"postgres": {"id": "kNhW2DUZwyFCsZ22", "name": "Postgres account"}}, "typeVersion": 2.6}, {"id": "53c1442f-9c4d-4ed2-baee-68812d199df3", "name": "Count Results", "type": "n8n-nodes-base.code", "position": [1100, 90], "parameters": {"mode": "runOnceForAllItems", "jsCode": "const items = $input.all();\nconst resultCount = items.length;\nconst webhookNode = $('Webhook').first()?.json?.body || {};\nconst startParams = Object.keys(webhookNode).length > 0 ? webhookNode : {\n  platform: 'naver_blog,youtube,bilibili',\n  followers_min: 1000,\n  followers_max: 1000000,\n  niche: '\ud328\uc158',\n  category: '\ud328\uc158',\n  country: 'KR'\n};\n\nreturn [{\n  json: {\n    search_params: {\n      platform: startParams.platform || startParams.platforms,\n      followers_min: startParams.followers_min,\n      followers_max: startParams.followers_max,\n      niche: startParams.niche,\n      category: startParams.category,\n      country: startParams.country\n    },\n    result_count: resultCount,\n    new_count: resultCount === 0 ? 0 : Math.max(1, Math.floor(resultCount * 0.7))\n  }\n}];", "language": "javaScript"}, "typeVersion": 2}, {"id": "0e0278e4-2b0e-43a6-a0b5-fa3ee3b97a54", "name": "Insert Search Log", "type": "n8n-nodes-base.postgres", "position": [1320, 90], "parameters": {"query": "INSERT INTO search_logs (search_params, result_count, new_count)\nVALUES (\n  '{{ JSON.stringify($json.search_params) }}'::jsonb, \n  {{ $json.result_count }}, \n  {{ $json.new_count }}\n);", "operation": "executeQuery"}, "credentials": {"postgres": {"id": "kNhW2DUZwyFCsZ22", "name": "Postgres account"}}, "typeVersion": 2.6}], "connections": {"Webhook": {"main": [[{"node": "Prepare Search Queries", "type": "main", "index": 0}]]}, "HTTP Request": {"main": [[{"node": "Parse Handles", "type": "main", "index": 0}]]}, "Count Results": {"main": [[{"node": "Insert Search Log", "type": "main", "index": 0}]]}, "Parse Handles": {"main": [[{"node": "UPSERT Influencers", "type": "main", "index": 0}]]}, "Schedule Trigger": {"main": [[{"node": "Prepare Search Queries", "type": "main", "index": 0}]]}, "UPSERT Influencers": {"main": [[{"node": "Count Results", "type": "main", "index": 0}]]}, "Prepare Search Queries": {"main": [[{"node": "HTTP Request", "type": "main", "index": 0}]]}}, "settings": {"executionOrder": "v1", "availableInMCP": true, "binaryMode": "separate"}, "staticData": {"node:Schedule Trigger": {"recurrenceRules": []}}, "meta": {"aiBuilderAssisted": true, "builderVariant": "mcp"}, "pinData": {"Webhook": [{"json": {"body": {"platforms": ["naver_blog", "youtube", "bilibili"], "followers_min": 10000, "followers_max": 100000, "niche": "fashion", "country": "ALL", "category": "fashion"}}}]}, "versionId": "46123377-ffcf-450d-b5bc-f012afec9320", "activeVersionId": "46123377-ffcf-450d-b5bc-f012afec9320", "versionCounter": 48, "triggerCount": 2, "tags": [], "shared": [{"updatedAt": "2026-06-15T13:17:51.972Z", "createdAt": "2026-06-15T13:17:51.972Z", "role": "workflow:owner", "workflowId": "l7viYNl8gEenBztB", "projectId": "elBzhGC6Cd79jUEr", "project": {"updatedAt": "2026-05-27T08:58:58.050Z", "createdAt": "2026-05-27T08:58:16.676Z", "id": "elBzhGC6Cd79jUEr", "name": "Taehyung Cho <thcho77@gmail.com>", "type": "personal", "icon": null, "description": null, "creatorId": "42e01500-3e90-478b-9fd1-86a2c1e91979"}}], "versionMetadata": {"name": "Version 46123377", "description": ""}}